{"title":[{"lat":"XVI.—","eng":"XVI.—"},{"lat":" ","eng":" "},{"lat":"SPARTANICA","eng":"SPARTAN"},{"lat":" ","eng":" "},{"lat":"BREVITAS.","eng":"BREVITY."}],"paragraphs":[{"words":[{"lat":"85.—","eng":"85.—"},{"lat":" ","eng":" "},{"lat":"Samii","eng":"Samians"},{"lat":" ","eng":" "},{"lat":"olim,","eng":"once,"},{"lat":" ","eng":" "},{"lat":"a","eng":"by"},{"lat":" ","eng":" "},{"lat":"Polycrate","eng":"Polycrates"},{"lat":" ","eng":" "},{"lat":"expulsi,","eng":"expelled,"},{"lat":" ","eng":" "},{"lat":"Spartam","eng":"To Sparta"},{"lat":" ","eng":" "},{"lat":"venerunt.","eng":"came."},{"lat":" ","eng":" "},{"lat":"Introducti","eng":"Introduced"},{"lat":" ","eng":" "},{"lat":"apud","eng":"to"},{"lat":" ","eng":" "},{"lat":"Ephoros","eng":"Ephors"},{"lat":" ","eng":" "},{"lat":"multa","eng":"many"},{"lat":" ","eng":" "},{"lat":"fecerunt","eng":"made"},{"lat":" ","eng":" "},{"lat":"verba,","eng":"words,"},{"lat":" ","eng":" "},{"lat":"opem","eng":"help"},{"lat":" ","eng":" "},{"lat":"orantes.","eng":"begging."},{"lat":" ","eng":" "},{"lat":"At","eng":"But"},{"lat":" ","eng":" "},{"lat":"illi","eng":"they"},{"lat":" ","eng":" "},{"lat":"responderunt:","eng":"replied:"},{"lat":" ‘","eng":" ‘"},{"lat":"Priora","eng":"Former"},{"lat":" ","eng":" "},{"lat":"verba","eng":"verba"},{"lat":" ","eng":" "},{"lat":"obliti","eng":"forgotten"},{"lat":" ","eng":" "},{"lat":"sumus,","eng":"we are,"},{"lat":" ","eng":" "},{"lat":"posteriora","eng":"latter"},{"lat":" ","eng":" "},{"lat":"non","eng":"not"},{"lat":" ","eng":" "},{"lat":"intelligimus.’","eng":"understand.’"},{"lat":" ","eng":" "},{"lat":"Post","eng":"After"},{"lat":" ","eng":" "},{"lat":"haec","eng":"this"},{"lat":" ","eng":" "},{"lat":"iterum","eng":"again"},{"lat":" ","eng":" "},{"lat":"introducti,","eng":"introducti,"},{"lat":" ","eng":" "},{"lat":"saccum","eng":"sack"},{"lat":" ","eng":" "},{"lat":"ferentes","eng":"carrying"},{"lat":" ","eng":" "},{"lat":"nihil","eng":"nothing"},{"lat":" ","eng":" "},{"lat":"aliud","eng":"else"},{"lat":" ","eng":" "},{"lat":"dixerunt,","eng":"said,"},{"lat":" ","eng":" "},{"lat":"nisi","eng":"except"},{"lat":" ","eng":" "},{"lat":"haec","eng":"these"},{"lat":" ","eng":" "},{"lat":"verba:","eng":"verba:"},{"lat":" ‘","eng":" ‘"},{"lat":"Saccus","eng":"Sack"},{"lat":" ","eng":" "},{"lat":"frumento","eng":"grain"},{"lat":" ","eng":" "},{"lat":"eget.’","eng":"needs.’"},{"lat":" ","eng":" "},{"lat":"His","eng":"To this"},{"lat":" ","eng":" "},{"lat":"Spartani","eng":"Spartans"},{"lat":" ","eng":" "},{"lat":"responderunt:","eng":"responderunt:"},{"lat":" ‘","eng":" ‘"},{"lat":"Nunc","eng":"Now"},{"lat":" ","eng":" "},{"lat":"intelligimus:","eng":"intelligimus:"},{"lat":" ","eng":" "},{"lat":"opem","eng":"opem"},{"lat":" ","eng":" "},{"lat":"vobis","eng":"you"},{"lat":" ","eng":" "},{"lat":"praestabimus.’","eng":"praestabimus.’"}]}]}